image_processing_braf/__init__.py
image_processing_braf/processing/__init__.py
image_processing_braf/processing/combination.py
image_processing_braf/processing/transformation.py
image_processing_braf/utils/__init__.py
image_processing_braf/utils/io.py
image_processing_braf/utils/plot.py
image_processing_braf-0.0.1.dist-info/METADATA
image_processing_braf-0.0.1.dist-info/WHEEL
image_processing_braf-0.0.1.dist-info/top_level.txt
image_processing_braf-0.0.1.dist-info/RECORD
