Metadata-Version: 2.1
Name: image-processing-braf
Version: 0.0.1
Summary: Image Processing Package using Skimage
Home-page: https://github.com/BiancaRAF/image_processing
Author: Professora Karina
License: UNKNOWN
Platform: UNKNOWN
Requires-Python: >=3.5
Requires-Dist: matplotlib
Requires-Dist: numpy
Requires-Dist: scikit-image (>=0.16.1)
